realsenseverif/Calibraton.py
realsenseverif/__init__.py
realsenseverif/frameCapture.py
realsenseverif/showFiles.py
realsenseverif/verification.py
realsenseverif-0.1.2.dist-info/METADATA
realsenseverif-0.1.2.dist-info/WHEEL
realsenseverif-0.1.2.dist-info/top_level.txt
realsenseverif-0.1.2.dist-info/RECORD
